AdaReader/__init__.py
AdaReader/datareader.py
tests/__init__.py
tests/test_datareader.py
AdaReader-0.0.2.dist-info/LICENSE
AdaReader-0.0.2.dist-info/METADATA
AdaReader-0.0.2.dist-info/WHEEL
AdaReader-0.0.2.dist-info/top_level.txt
AdaReader-0.0.2.dist-info/RECORD
