Metadata-Version: 2.2
Name: AdaReader
Version: 0.0.2
Summary: A versatile library for reading datasets from multiple formats and generating synthetic datasets.
Home-page: https://github.com/YousofLHC/flexi_datareader
Author: Yousof Ghalenoei
Author-email: yousof.ghalenoei2017@gmail.com
Classifier: Programming Language :: Python :: 3
Classifier: License :: OSI Approved :: MIT License
Classifier: Operating System :: OS Independent
Classifier: Intended Audience :: Developers
Classifier: Topic :: Software Development :: Libraries :: Python Modules
Requires-Python: >=3.6
License-File: LICENSE
Requires-Dist: pandas>=1.0
Requires-Dist: numpy>=1.18
Requires-Dist: scipy>=1.4
Requires-Dist: scikit-learn>=0.24
Dynamic: author
Dynamic: author-email
Dynamic: classifier
Dynamic: description
Dynamic: description-content-type
Dynamic: home-page
Dynamic: requires-dist
Dynamic: requires-python
Dynamic: summary
